osc_ingest_tools-0.5.5.dist-info/METADATA
osc_ingest_tools-0.5.5.dist-info/WHEEL
osc_ingest_tools-0.5.5.dist-info/entry_points.txt
osc_ingest_tools-0.5.5.dist-info/licenses/LICENSE
osc_ingest_trino/__init__.py
osc_ingest_trino/boto3_utils.py
osc_ingest_trino/dotenv_utils.py
osc_ingest_trino/sqlcols.py
osc_ingest_trino/sqltypes.py
osc_ingest_trino/trino_utils.py
osc_ingest_trino/unmanaged/__init__.py
osc_ingest_trino/unmanaged/unmanaged_hive_ingest.py
osc_ingest_tools-0.5.5.dist-info/RECORD
