Metadata-Version: 2.1
Name: osc-ingest-tools
Version: 0.5.5
Summary: OS-Climate Python tools to assist with standardized data ingestion workflows
Keywords: Climate,osc-ingest-tools,Finance
Author-Email: Michael Tiemann <72577720+MichaelTiemannOSC@users.noreply.github.com>
License: Apache-2.0
Classifier: Intended Audience :: Developers
Classifier: Intended Audience :: Science/Research
Classifier: License :: OSI Approved :: Apache Software License
Classifier: Operating System :: MacOS
Classifier: Operating System :: Microsoft :: Windows
Classifier: Operating System :: Unix
Classifier: Programming Language :: Python
Classifier: Programming Language :: Python :: 3
Classifier: Programming Language :: Python :: 3 :: Only
Classifier: Programming Language :: Python :: 3.12
Classifier: Programming Language :: Python :: 3.11
Classifier: Programming Language :: Python :: 3.10
Classifier: Topic :: Office/Business :: Financial
Classifier: Topic :: Scientific/Engineering
Classifier: Topic :: Software Development
Project-URL: Homepage, https://github.com/os-climate/osc-ingest-tools
Project-URL: Repository, https://github.com/os-climate/osc-ingest-tools
Project-URL: Downloads, https://github.com/os-climate/osc-ingest-tools/releases
Project-URL: Bug Tracker, https://github.com/os-climate/osc-ingest-tools/issues
Project-URL: Documentation, https://github.com/os-climate/osc-ingest-tools/tree/main/docs
Project-URL: Source Code, https://github.com/os-climate/osc-ingest-tools
Requires-Python: <3.13,>=3.10
Requires-Dist: trino[sqlalchemy]>=0.323
Requires-Dist: sqlalchemy>=2.0
Requires-Dist: pandas
Requires-Dist: python-dotenv
Requires-Dist: boto3
Requires-Dist: moto[s3]>=5.0.6
Requires-Dist: boto>=2.49.0
Requires-Dist: mypy-boto3-s3>=1.34.91
